xfers_sdk/__init__.py
xfers_sdk/_api_requestor.py
xfers_sdk/_config.py
xfers_sdk/_extract_params.py
xfers_sdk/_post_attributes.py
xfers_sdk/_xfers_param_injector.py
xfers_sdk/models/__init__.py
xfers_sdk/models/_base_query.py
xfers_sdk/models/_to_model.py
xfers_sdk/models/balance/__init__.py
xfers_sdk/models/balance/balance.py
xfers_sdk/models/balance/entity/balance.py
xfers_sdk/models/bank/__init__.py
xfers_sdk/models/bank/bank.py
xfers_sdk/models/bank/entity/bank.py
xfers_sdk/models/bank/entity/bank_account.py
xfers_sdk/models/disbursements/__init__.py
xfers_sdk/models/disbursements/disbursements.py
xfers_sdk/models/disbursements/entity/disbursements.py
xfers_sdk/models/payment/__init__.py
xfers_sdk/models/payment/entity/payment.py
xfers_sdk/models/payment/payment.py
xfers_sdk/models/payment_link/__init__.py
xfers_sdk/models/payment_link/entity/payment_link.py
xfers_sdk/models/payment_link/payment_link.py
xfers_sdk/models/payment_methods/__init__.py
xfers_sdk/models/payment_methods/entity/manage_payment_method.py
xfers_sdk/models/payment_methods/entity/payment_method.py
xfers_sdk/models/payment_methods/entity/payment_methods.py
xfers_sdk/models/payment_methods/payment_methods.py
xfers_sdk/network/__init__.py
xfers_sdk/network/http_client_interface.py
xfers_sdk/network/xfers_response.py
xfers_sdk/xfers.py
xfers_sdk/xfers_error.py
xfers_sdk-1.0.1.dist-info/WHEEL
xfers_sdk-1.0.1.dist-info/METADATA
xfers_sdk-1.0.1.dist-info/RECORD
