Metadata-Version: 2.1
Name: xfers-sdk
Version: 1.0.1
Summary: Xfers REST API Client for Python
License: MIT
Author: LandX Engineering
Author-email: tech@landx.id
Requires-Python: >=3.9,<4.0
Classifier: License :: OSI Approved :: MIT License
Classifier: Programming Language :: Python :: 3
Classifier: Programming Language :: Python :: 3.10
Classifier: Programming Language :: Python :: 3.9
Requires-Dist: dacite (>=1.6.0,<2.0.0)
Requires-Dist: pyhumps (>=3.5.3,<4.0.0)
Requires-Dist: requests (>=2.27.1,<3.0.0)
